odoo/addons/shopinvader_product_variant_selector/README.rst
odoo/addons/shopinvader_product_variant_selector/__init__.py
odoo/addons/shopinvader_product_variant_selector/__manifest__.py
odoo/addons/shopinvader_product_variant_selector/data/ir_export_product.xml
odoo/addons/shopinvader_product_variant_selector/demo/product_demo.xml
odoo/addons/shopinvader_product_variant_selector/i18n/shopinvader_product_variant_selector.pot
odoo/addons/shopinvader_product_variant_selector/models/__init__.py
odoo/addons/shopinvader_product_variant_selector/models/shopinvader_variant.py
odoo/addons/shopinvader_product_variant_selector/readme/CONTRIBUTORS.rst
odoo/addons/shopinvader_product_variant_selector/readme/CREDITS.rst
odoo/addons/shopinvader_product_variant_selector/readme/DESCRIPTION.rst
odoo/addons/shopinvader_product_variant_selector/static/description/index.html
odoo/addons/shopinvader_product_variant_selector/tests/__init__.py
odoo/addons/shopinvader_product_variant_selector/tests/test_shopinvader_variant.py
odoo14_addon_shopinvader_product_variant_selector-14.0.1.0.1.dev4.dist-info/METADATA
odoo14_addon_shopinvader_product_variant_selector-14.0.1.0.1.dev4.dist-info/WHEEL
odoo14_addon_shopinvader_product_variant_selector-14.0.1.0.1.dev4.dist-info/top_level.txt
odoo14_addon_shopinvader_product_variant_selector-14.0.1.0.1.dev4.dist-info/RECORD
