Metadata-Version: 2.1
Name: odoo14-addon-shopinvader_product_variant_selector
Version: 14.0.1.0.1.dev4
Summary: Ease creation of variants selector on shopinvader sites
Home-page: https://github.com/shopinvader/odoo-shopinvader
Author: Akretion
License: AGPL-3
Classifier: Programming Language :: Python
Classifier: Framework :: Odoo
Classifier: Framework :: Odoo :: 14.0
Classifier: License :: OSI Approved :: GNU Affero General Public License v3
Requires-Python: >=3.6
Requires-Dist: odoo14-addon-shopinvader
Requires-Dist: odoo <14.1dev,>=14.0a
